biology_files-0.3.4.dist-info/METADATA
biology_files-0.3.4.dist-info/WHEEL
biology_files-0.3.4.dist-info/licenses/PYPI_LICENSE
biology_files/__init__.py
biology_files/biology_files.abi3.so
biology_files-0.3.4.dist-info/RECORD
