Metadata-Version: 2.4
Name: biology_files
Version: 0.3.4
Classifier: Intended Audience :: Science/Research
Classifier: Topic :: Scientific/Engineering :: Bio-Informatics
Classifier: Programming Language :: Rust
Classifier: Programming Language :: Python :: Implementation :: CPython
Classifier: Programming Language :: Python :: Implementation :: PyPy
License-File: PYPI_LICENSE
Summary: Save and load common biology file formats
Keywords: mol2,sdf,mmcif,amber,biology
Author-email: David O'Connor <the_alchemist@fastmail.com>
Requires-Python: >=3.10
Project-URL: homepage, https://github.com/David-OConnor/bio_files
Project-URL: repository, https://github.com/David-OConnor/bio_files
Project-URL: documentation, https://docs.rs/bio_files
